bsv_wallet_toolbox/__init__.py
bsv_wallet_toolbox/auth_fetch.py
bsv_wallet_toolbox/certificate.py
bsv_wallet_toolbox/local_kv_store.py
bsv_wallet_toolbox/private_key.py
bsv_wallet_toolbox/single_writer_multi_reader_lock.py
bsv_wallet_toolbox/types.py
bsv_wallet_toolbox/wallet.py
bsv_wallet_toolbox/abi/__init__.py
bsv_wallet_toolbox/abi/serializer.py
bsv_wallet_toolbox/assembler/__init__.py
bsv_wallet_toolbox/assembler/create_action_tx_assembler.py
bsv_wallet_toolbox/brc29/__init__.py
bsv_wallet_toolbox/brc29/address.py
bsv_wallet_toolbox/brc29/template.py
bsv_wallet_toolbox/brc29/types.py
bsv_wallet_toolbox/brc29/utils.py
bsv_wallet_toolbox/errors/__init__.py
bsv_wallet_toolbox/errors/wallet_errors.py
bsv_wallet_toolbox/manager/__init__.py
bsv_wallet_toolbox/manager/permission_token_parser.py
bsv_wallet_toolbox/manager/permission_types.py
bsv_wallet_toolbox/manager/simple_wallet_manager.py
bsv_wallet_toolbox/manager/wallet_interface.py
bsv_wallet_toolbox/manager/wallet_permissions_manager.py
bsv_wallet_toolbox/manager/wallet_settings_manager.py
bsv_wallet_toolbox/monitor/__init__.py
bsv_wallet_toolbox/monitor/monitor.py
bsv_wallet_toolbox/monitor/monitor_daemon.py
bsv_wallet_toolbox/monitor/wallet_monitor_task.py
bsv_wallet_toolbox/monitor/tasks/__init__.py
bsv_wallet_toolbox/monitor/tasks/task_check_for_proofs.py
bsv_wallet_toolbox/monitor/tasks/task_check_no_sends.py
bsv_wallet_toolbox/monitor/tasks/task_clock.py
bsv_wallet_toolbox/monitor/tasks/task_fail_abandoned.py
bsv_wallet_toolbox/monitor/tasks/task_monitor_call_history.py
bsv_wallet_toolbox/monitor/tasks/task_new_header.py
bsv_wallet_toolbox/monitor/tasks/task_purge.py
bsv_wallet_toolbox/monitor/tasks/task_reorg.py
bsv_wallet_toolbox/monitor/tasks/task_review_status.py
bsv_wallet_toolbox/monitor/tasks/task_send_waiting.py
bsv_wallet_toolbox/monitor/tasks/task_sync_when_idle.py
bsv_wallet_toolbox/monitor/tasks/task_un_fail.py
bsv_wallet_toolbox/rpc/__init__.py
bsv_wallet_toolbox/rpc/storage_client.py
bsv_wallet_toolbox-2.0.1.dist-info/METADATA
bsv_wallet_toolbox-2.0.1.dist-info/WHEEL
bsv_wallet_toolbox-2.0.1.dist-info/RECORD
