Metadata-Version: 2.4
Name: bsv-wallet-toolbox
Version: 2.0.1
Summary: BRC-100 compliant Bitcoin SV wallet implementation
Author: BSV Blockchain Association
License: Open BSV License version 4
Keywords: bitcoin,brc-100,bsv,wallet
Classifier: Development Status :: 3 - Alpha
Classifier: Intended Audience :: Developers
Classifier: Programming Language :: Python :: 3
Classifier: Programming Language :: Python :: 3.11
Classifier: Programming Language :: Python :: 3.12
Requires-Python: >=3.11
Requires-Dist: bsv-middleware>=2.0.2
Requires-Dist: bsv-sdk>=2.0.0b1
Requires-Dist: python-dotenv>=1.0
Requires-Dist: requests>=2.31
Requires-Dist: sqlalchemy>=2.0
Provides-Extra: db-mysql
Requires-Dist: pymysql>=1.1; extra == 'db-mysql'
Provides-Extra: db-postgres
Requires-Dist: psycopg[binary]>=3.1; extra == 'db-postgres'
Provides-Extra: dev
Requires-Dist: black>=23.0.0; extra == 'dev'
Requires-Dist: mypy>=1.0.0; extra == 'dev'
Requires-Dist: psycopg[binary]>=3.1; extra == 'dev'
Requires-Dist: pymysql>=1.1; extra == 'dev'
Requires-Dist: pytest-asyncio>=0.23.0; extra == 'dev'
Requires-Dist: pytest-cov>=4.0.0; extra == 'dev'
Requires-Dist: pytest>=7.0.0; extra == 'dev'
Requires-Dist: ruff>=0.1.0; extra == 'dev'
